setup.py
mobileapart/__init__.py
mobileapart.django.newsletter.egg-info/PKG-INFO
mobileapart.django.newsletter.egg-info/SOURCES.txt
mobileapart.django.newsletter.egg-info/dependency_links.txt
mobileapart.django.newsletter.egg-info/namespace_packages.txt
mobileapart.django.newsletter.egg-info/not-zip-safe
mobileapart.django.newsletter.egg-info/requires.txt
mobileapart.django.newsletter.egg-info/top_level.txt
mobileapart/django/__init__.py
mobileapart/django/newsletter/__init__.py
mobileapart/django/newsletter/models.py
mobileapart/django/newsletter/settings.py
mobileapart/django/newsletter/utils.py
mobileapart/django/newsletter/admin/__init__.py
mobileapart/django/newsletter/admin/contact.py
mobileapart/django/newsletter/admin/mailinglist.py
mobileapart/django/newsletter/admin/mailingstats.py
mobileapart/django/newsletter/admin/newsletter.py
mobileapart/django/newsletter/management/__init__.py
mobileapart/django/newsletter/management/commands/__init__.py
mobileapart/django/newsletter/migrations/__init__.py
mobileapart/django/newsletter/urls/__init__.py
mobileapart/django/newsletter/urls/newsletter.py
mobileapart/django/newsletter/views/__init__.py