Metadata-Version: 1.0
Name: mobileapart.django.newsletter
Version: 0.6.2
Summary: A Django app for sending newsletter by email to a contact list.
Home-page: https://github.com/ledil/mobileapart-django-newsletter
Author: Leonardo Di Lella
Author-email: leonardo.dilella@mobileapart.com
License: BSD License
Keywords: django,newsletter,mailing
Platform: UNKNOWN
Classifier: Framework :: Django
Classifier: Programming Language :: Python
Classifier: Environment :: Web Environment
Classifier: Intended Audience :: Developers
Classifier: Operating System :: OS Independent
Classifier: License :: OSI Approved :: BSD License
Classifier: Development Status :: 5 - Production/Stable
Classifier: Topic :: Software Development :: Libraries :: Python Modules
